sea_names/__init__.py
sea_names/cache.py
sea_names/cli.py
sea_names/geo.py
sea_names/log.py
sea_names/logging.conf
sea_names/processing.py
sea_names-0.4.0.dist-info/licenses/AUTHORS.rst
sea_names-0.4.0.dist-info/licenses/LICENSE
sea_names-0.4.0.dist-info/METADATA
sea_names-0.4.0.dist-info/WHEEL
sea_names-0.4.0.dist-info/entry_points.txt
sea_names-0.4.0.dist-info/top_level.txt
sea_names-0.4.0.dist-info/RECORD
