Metadata-Version: 2.4
Name: sea-names
Version: 0.4.0
Summary: Determine the sea-name of any arbitrary point or shapely geometry.
Home-page: http://github.com/axiom-data-science/sea-names/
Author: Luke Campbell
Author-email: luke@axds.co
License: MIT license
Keywords: sea-names
Classifier: Development Status :: 2 - Pre-Alpha
Classifier: Intended Audience :: Developers
Classifier: License :: OSI Approved :: MIT License
Classifier: Natural Language :: English
Classifier: Programming Language :: Python :: 3
Classifier: Programming Language :: Python :: 3.6
Classifier: Programming Language :: Python :: 3.7
Classifier: Programming Language :: Python :: 3.8
License-File: LICENSE
License-File: AUTHORS.rst
Requires-Dist: appdirs
Requires-Dist: numpy
Requires-Dist: requests
Requires-Dist: shapely
Dynamic: author
Dynamic: author-email
Dynamic: classifier
Dynamic: description
Dynamic: home-page
Dynamic: keywords
Dynamic: license
Dynamic: license-file
Dynamic: requires-dist
Dynamic: summary
